python_ron-0.2.5.dist-info/METADATA
python_ron-0.2.5.dist-info/WHEEL
pyron/__init__.py
pyron/__init__.pyi
pyron/py.typed
pyron/pyron.pypy37-pp73-x86_64-linux-gnu.so
python_ron-0.2.5.dist-info/RECORD
