Metadata-Version: 2.1
Name: python-ron
Version: 0.2.5
